ledger2bql/__init__.py
ledger2bql/assert_command.py
ledger2bql/balance.py
ledger2bql/date_parser.py
ledger2bql/logging_utils.py
ledger2bql/lots.py
ledger2bql/main.py
ledger2bql/price.py
ledger2bql/query.py
ledger2bql/register.py
ledger2bql/utils.py
ledger2bql-1.17.0.dist-info/METADATA
ledger2bql-1.17.0.dist-info/WHEEL
ledger2bql-1.17.0.dist-info/entry_points.txt
ledger2bql-1.17.0.dist-info/licenses/LICENSE
ledger2bql-1.17.0.dist-info/RECORD
