Metadata-Version: 2.4
Name: ledger2bql
Version: 1.17.0
Summary: Translate Ledger CLI query syntax into BQL
Project-URL: Repository, https://github.com/alensiljak/ledger2bql
Author: Alen Šiljak
License-File: LICENSE
Requires-Python: >=3.12
Requires-Dist: beancount>=3.2.0
Requires-Dist: beanquery>=0.2.0
Requires-Dist: click>=8.3.0
Requires-Dist: dotenv>=0.9.9
Requires-Dist: loguru>=0.7.0
Requires-Dist: tabulate>=0.9.0
